ai4gs/__init__.py
ai4gs/config.py
ai4gs/main.py
ai4gs/utils.py
ai4gs-0.0.1.dist-info/licenses/LICENSE
ai4gs-0.0.1.dist-info/METADATA
ai4gs-0.0.1.dist-info/WHEEL
ai4gs-0.0.1.dist-info/entry_points.txt
ai4gs-0.0.1.dist-info/top_level.txt
ai4gs-0.0.1.dist-info/RECORD
