Metadata-Version: 2.4
Name: ai4gs
Version: 0.0.1
Summary: AI-Powered Google Scholar Assistant
Author: Li Mengke
License: MIT License
Project-URL: Homepage, https://github.com/LIMENGKE24/AI-Agent-GoogleScholarAlertEmail
Requires-Python: >=3.8
License-File: LICENSE
Requires-Dist: beautifulsoup4
Requires-Dist: python-dotenv
Requires-Dist: markdown
Requires-Dist: anthropic
Dynamic: license-file
